{
  "metadata" : {
    "identifier" : "https://nhattruyenz.com/truyen-tranh/cha-oi-con-khong-muon-ket-hon-dau",
    "title" : "Cha Ơi Con Không Muốn Kết Hôn Đâu",
    "subtitle" : null,
    "author" : null,
    "narrator" : null,
    "language" : "vi",
    "description" : null,
    "publisher" : "N/A",
    "subject" : null,
    "modified" : null,
    "published" : "2023-04-30",
    "duration" : 0,
    "abridged" : false,
    "conformsTo" : "https://readium.org/webpub-manifest/profiles/divina",
    "numberOfPages" : 112,
    "readingProgression" : "ttb",
    "belongsTo" : null,
    "presentation" : {
      "fit" : "width",
      "overflow" : "scrolled",
      "continuous" : true
    },
    "@type" : null,
    "schema:license" : null
  },
  "links" : [ {
    "rel" : "self",
    "href" : "https://raw.githubusercontent.com/thuvienonline40/book_storage_collection/main/comic_manifest.json",
    "type" : "application/divina+json"
  } ],
  "readingOrder" : [ {
    "href" : "https://img.abctruyen.xyz/uploads/19088/chuong-89/1.jpg",
    "type" : "image/jpeg",
    "bitrate" : 0,
    "duration" : 0,
    "title" : null,
    "properties" : null,
    "alternate" : [ {
      "href" : "https://i2.wp.com/img.abctruyen.xyz/uploads/19088/chuong-89/1.jpg",
      "type" : "image/jpeg",
      "bitrate" : 0,
      "duration" : 0,
      "title" : null,
      "properties" : null,
      "alternate" : null
    } ]
  }, {
    "href" : "https://img.abctruyen.xyz/uploads/19088/chuong-89/2.jpg",
    "type" : "image/jpeg",
    "bitrate" : 0,
    "duration" : 0,
    "title" : null,
    "properties" : null,
    "alternate" : [ {
      "href" : "https://i2.wp.com/img.abctruyen.xyz/uploads/19088/chuong-89/2.jpg",
      "type" : "image/jpeg",
      "bitrate" : 0,
      "duration" : 0,
      "title" : null,
      "properties" : null,
      "alternate" : null
    } ]
  }, {
    "href" : "https://img.abctruyen.xyz/uploads/19088/chuong-89/3.jpg",
    "type" : "image/jpeg",
    "bitrate" : 0,
    "duration" : 0,
    "title" : null,
    "properties" : null,
    "alternate" : [ {
      "href" : "https://i2.wp.com/img.abctruyen.xyz/uploads/19088/chuong-89/3.jpg",
      "type" : "image/jpeg",
      "bitrate" : 0,
      "duration" : 0,
      "title" : null,
      "properties" : null,
      "alternate" : null
    } ]
  }, {
    "href" : "https://img.abctruyen.xyz/uploads/19088/chuong-89/4.jpg",
    "type" : "image/jpeg",
    "bitrate" : 0,
    "duration" : 0,
    "title" : null,
    "properties" : null,
    "alternate" : [ {
      "href" : "https://i2.wp.com/img.abctruyen.xyz/uploads/19088/chuong-89/4.jpg",
      "type" : "image/jpeg",
      "bitrate" : 0,
      "duration" : 0,
      "title" : null,
      "properties" : null,
      "alternate" : null
    } ]
  }, {
    "href" : "https://img.abctruyen.xyz/uploads/19088/chuong-89/5.jpg",
    "type" : "image/jpeg",
    "bitrate" : 0,
    "duration" : 0,
    "title" : null,
    "properties" : null,
    "alternate" : [ {
      "href" : "https://i2.wp.com/img.abctruyen.xyz/uploads/19088/chuong-89/5.jpg",
      "type" : "image/jpeg",
      "bitrate" : 0,
      "duration" : 0,
      "title" : null,
      "properties" : null,
      "alternate" : null
    } ]
  }, {
    "href" : "https://img.abctruyen.xyz/uploads/19088/chuong-89/6.jpg",
    "type" : "image/jpeg",
    "bitrate" : 0,
    "duration" : 0,
    "title" : null,
    "properties" : null,
    "alternate" : [ {
      "href" : "https://i2.wp.com/img.abctruyen.xyz/uploads/19088/chuong-89/6.jpg",
      "type" : "image/jpeg",
      "bitrate" : 0,
      "duration" : 0,
      "title" : null,
      "properties" : null,
      "alternate" : null
    } ]
  }, {
    "href" : "https://img.abctruyen.xyz/uploads/19088/chuong-89/7.jpg",
    "type" : "image/jpeg",
    "bitrate" : 0,
    "duration" : 0,
    "title" : null,
    "properties" : null,
    "alternate" : [ {
      "href" : "https://i2.wp.com/img.abctruyen.xyz/uploads/19088/chuong-89/7.jpg",
      "type" : "image/jpeg",
      "bitrate" : 0,
      "duration" : 0,
      "title" : null,
      "properties" : null,
      "alternate" : null
    } ]
  }, {
    "href" : "https://img.abctruyen.xyz/uploads/19088/chuong-89/8.jpg",
    "type" : "image/jpeg",
    "bitrate" : 0,
    "duration" : 0,
    "title" : null,
    "properties" : null,
    "alternate" : [ {
      "href" : "https://i2.wp.com/img.abctruyen.xyz/uploads/19088/chuong-89/8.jpg",
      "type" : "image/jpeg",
      "bitrate" : 0,
      "duration" : 0,
      "title" : null,
      "properties" : null,
      "alternate" : null
    } ]
  }, {
    "href" : "https://img.abctruyen.xyz/uploads/19088/chuong-89/9.jpg",
    "type" : "image/jpeg",
    "bitrate" : 0,
    "duration" : 0,
    "title" : null,
    "properties" : null,
    "alternate" : [ {
      "href" : "https://i2.wp.com/img.abctruyen.xyz/uploads/19088/chuong-89/9.jpg",
      "type" : "image/jpeg",
      "bitrate" : 0,
      "duration" : 0,
      "title" : null,
      "properties" : null,
      "alternate" : null
    } ]
  }, {
    "href" : "https://img.abctruyen.xyz/uploads/19088/chuong-89/10.jpg",
    "type" : "image/jpeg",
    "bitrate" : 0,
    "duration" : 0,
    "title" : null,
    "properties" : null,
    "alternate" : [ {
      "href" : "https://i2.wp.com/img.abctruyen.xyz/uploads/19088/chuong-89/10.jpg",
      "type" : "image/jpeg",
      "bitrate" : 0,
      "duration" : 0,
      "title" : null,
      "properties" : null,
      "alternate" : null
    } ]
  }, {
    "href" : "https://img.abctruyen.xyz/uploads/19088/chuong-89/11.jpg",
    "type" : "image/jpeg",
    "bitrate" : 0,
    "duration" : 0,
    "title" : null,
    "properties" : null,
    "alternate" : [ {
      "href" : "https://i2.wp.com/img.abctruyen.xyz/uploads/19088/chuong-89/11.jpg",
      "type" : "image/jpeg",
      "bitrate" : 0,
      "duration" : 0,
      "title" : null,
      "properties" : null,
      "alternate" : null
    } ]
  }, {
    "href" : "https://img.abctruyen.xyz/uploads/19088/chuong-89/12.jpg",
    "type" : "image/jpeg",
    "bitrate" : 0,
    "duration" : 0,
    "title" : null,
    "properties" : null,
    "alternate" : [ {
      "href" : "https://i2.wp.com/img.abctruyen.xyz/uploads/19088/chuong-89/12.jpg",
      "type" : "image/jpeg",
      "bitrate" : 0,
      "duration" : 0,
      "title" : null,
      "properties" : null,
      "alternate" : null
    } ]
  }, {
    "href" : "https://img.abctruyen.xyz/uploads/19088/chuong-89/13.jpg",
    "type" : "image/jpeg",
    "bitrate" : 0,
    "duration" : 0,
    "title" : null,
    "properties" : null,
    "alternate" : [ {
      "href" : "https://i2.wp.com/img.abctruyen.xyz/uploads/19088/chuong-89/13.jpg",
      "type" : "image/jpeg",
      "bitrate" : 0,
      "duration" : 0,
      "title" : null,
      "properties" : null,
      "alternate" : null
    } ]
  }, {
    "href" : "https://img.abctruyen.xyz/uploads/19088/chuong-89/14.jpg",
    "type" : "image/jpeg",
    "bitrate" : 0,
    "duration" : 0,
    "title" : null,
    "properties" : null,
    "alternate" : [ {
      "href" : "https://i2.wp.com/img.abctruyen.xyz/uploads/19088/chuong-89/14.jpg",
      "type" : "image/jpeg",
      "bitrate" : 0,
      "duration" : 0,
      "title" : null,
      "properties" : null,
      "alternate" : null
    } ]
  }, {
    "href" : "https://img.abctruyen.xyz/uploads/19088/chuong-89/15.jpg",
    "type" : "image/jpeg",
    "bitrate" : 0,
    "duration" : 0,
    "title" : null,
    "properties" : null,
    "alternate" : [ {
      "href" : "https://i2.wp.com/img.abctruyen.xyz/uploads/19088/chuong-89/15.jpg",
      "type" : "image/jpeg",
      "bitrate" : 0,
      "duration" : 0,
      "title" : null,
      "properties" : null,
      "alternate" : null
    } ]
  }, {
    "href" : "https://img.abctruyen.xyz/uploads/19088/chuong-89/16.jpg",
    "type" : "image/jpeg",
    "bitrate" : 0,
    "duration" : 0,
    "title" : null,
    "properties" : null,
    "alternate" : [ {
      "href" : "https://i2.wp.com/img.abctruyen.xyz/uploads/19088/chuong-89/16.jpg",
      "type" : "image/jpeg",
      "bitrate" : 0,
      "duration" : 0,
      "title" : null,
      "properties" : null,
      "alternate" : null
    } ]
  }, {
    "href" : "https://img.abctruyen.xyz/uploads/19088/chuong-89/17.jpg",
    "type" : "image/jpeg",
    "bitrate" : 0,
    "duration" : 0,
    "title" : null,
    "properties" : null,
    "alternate" : [ {
      "href" : "https://i2.wp.com/img.abctruyen.xyz/uploads/19088/chuong-89/17.jpg",
      "type" : "image/jpeg",
      "bitrate" : 0,
      "duration" : 0,
      "title" : null,
      "properties" : null,
      "alternate" : null
    } ]
  }, {
    "href" : "https://img.abctruyen.xyz/uploads/19088/chuong-89/18.jpg",
    "type" : "image/jpeg",
    "bitrate" : 0,
    "duration" : 0,
    "title" : null,
    "properties" : null,
    "alternate" : [ {
      "href" : "https://i2.wp.com/img.abctruyen.xyz/uploads/19088/chuong-89/18.jpg",
      "type" : "image/jpeg",
      "bitrate" : 0,
      "duration" : 0,
      "title" : null,
      "properties" : null,
      "alternate" : null
    } ]
  }, {
    "href" : "https://img.abctruyen.xyz/uploads/19088/chuong-89/19.jpg",
    "type" : "image/jpeg",
    "bitrate" : 0,
    "duration" : 0,
    "title" : null,
    "properties" : null,
    "alternate" : [ {
      "href" : "https://i2.wp.com/img.abctruyen.xyz/uploads/19088/chuong-89/19.jpg",
      "type" : "image/jpeg",
      "bitrate" : 0,
      "duration" : 0,
      "title" : null,
      "properties" : null,
      "alternate" : null
    } ]
  }, {
    "href" : "https://img.abctruyen.xyz/uploads/19088/chuong-89/20.jpg",
    "type" : "image/jpeg",
    "bitrate" : 0,
    "duration" : 0,
    "title" : null,
    "properties" : null,
    "alternate" : [ {
      "href" : "https://i2.wp.com/img.abctruyen.xyz/uploads/19088/chuong-89/20.jpg",
      "type" : "image/jpeg",
      "bitrate" : 0,
      "duration" : 0,
      "title" : null,
      "properties" : null,
      "alternate" : null
    } ]
  }, {
    "href" : "https://img.abctruyen.xyz/uploads/19088/chuong-89/21.jpg",
    "type" : "image/jpeg",
    "bitrate" : 0,
    "duration" : 0,
    "title" : null,
    "properties" : null,
    "alternate" : [ {
      "href" : "https://i2.wp.com/img.abctruyen.xyz/uploads/19088/chuong-89/21.jpg",
      "type" : "image/jpeg",
      "bitrate" : 0,
      "duration" : 0,
      "title" : null,
      "properties" : null,
      "alternate" : null
    } ]
  }, {
    "href" : "https://img.abctruyen.xyz/uploads/19088/chuong-89/22.jpg",
    "type" : "image/jpeg",
    "bitrate" : 0,
    "duration" : 0,
    "title" : null,
    "properties" : null,
    "alternate" : [ {
      "href" : "https://i2.wp.com/img.abctruyen.xyz/uploads/19088/chuong-89/22.jpg",
      "type" : "image/jpeg",
      "bitrate" : 0,
      "duration" : 0,
      "title" : null,
      "properties" : null,
      "alternate" : null
    } ]
  }, {
    "href" : "https://img.abctruyen.xyz/uploads/19088/chuong-89/23.jpg",
    "type" : "image/jpeg",
    "bitrate" : 0,
    "duration" : 0,
    "title" : null,
    "properties" : null,
    "alternate" : [ {
      "href" : "https://i2.wp.com/img.abctruyen.xyz/uploads/19088/chuong-89/23.jpg",
      "type" : "image/jpeg",
      "bitrate" : 0,
      "duration" : 0,
      "title" : null,
      "properties" : null,
      "alternate" : null
    } ]
  }, {
    "href" : "https://img.abctruyen.xyz/uploads/19088/chuong-89/24.jpg",
    "type" : "image/jpeg",
    "bitrate" : 0,
    "duration" : 0,
    "title" : null,
    "properties" : null,
    "alternate" : [ {
      "href" : "https://i2.wp.com/img.abctruyen.xyz/uploads/19088/chuong-89/24.jpg",
      "type" : "image/jpeg",
      "bitrate" : 0,
      "duration" : 0,
      "title" : null,
      "properties" : null,
      "alternate" : null
    } ]
  }, {
    "href" : "https://img.abctruyen.xyz/uploads/19088/chuong-89/25.jpg",
    "type" : "image/jpeg",
    "bitrate" : 0,
    "duration" : 0,
    "title" : null,
    "properties" : null,
    "alternate" : [ {
      "href" : "https://i2.wp.com/img.abctruyen.xyz/uploads/19088/chuong-89/25.jpg",
      "type" : "image/jpeg",
      "bitrate" : 0,
      "duration" : 0,
      "title" : null,
      "properties" : null,
      "alternate" : null
    } ]
  }, {
    "href" : "https://img.abctruyen.xyz/uploads/19088/chuong-89/26.jpg",
    "type" : "image/jpeg",
    "bitrate" : 0,
    "duration" : 0,
    "title" : null,
    "properties" : null,
    "alternate" : [ {
      "href" : "https://i2.wp.com/img.abctruyen.xyz/uploads/19088/chuong-89/26.jpg",
      "type" : "image/jpeg",
      "bitrate" : 0,
      "duration" : 0,
      "title" : null,
      "properties" : null,
      "alternate" : null
    } ]
  }, {
    "href" : "https://img.abctruyen.xyz/uploads/19088/chuong-89/27.jpg",
    "type" : "image/jpeg",
    "bitrate" : 0,
    "duration" : 0,
    "title" : null,
    "properties" : null,
    "alternate" : [ {
      "href" : "https://i2.wp.com/img.abctruyen.xyz/uploads/19088/chuong-89/27.jpg",
      "type" : "image/jpeg",
      "bitrate" : 0,
      "duration" : 0,
      "title" : null,
      "properties" : null,
      "alternate" : null
    } ]
  }, {
    "href" : "https://img.abctruyen.xyz/uploads/19088/chuong-89/28.jpg",
    "type" : "image/jpeg",
    "bitrate" : 0,
    "duration" : 0,
    "title" : null,
    "properties" : null,
    "alternate" : [ {
      "href" : "https://i2.wp.com/img.abctruyen.xyz/uploads/19088/chuong-89/28.jpg",
      "type" : "image/jpeg",
      "bitrate" : 0,
      "duration" : 0,
      "title" : null,
      "properties" : null,
      "alternate" : null
    } ]
  }, {
    "href" : "https://img.abctruyen.xyz/uploads/19088/chuong-89/29.jpg",
    "type" : "image/jpeg",
    "bitrate" : 0,
    "duration" : 0,
    "title" : null,
    "properties" : null,
    "alternate" : [ {
      "href" : "https://i2.wp.com/img.abctruyen.xyz/uploads/19088/chuong-89/29.jpg",
      "type" : "image/jpeg",
      "bitrate" : 0,
      "duration" : 0,
      "title" : null,
      "properties" : null,
      "alternate" : null
    } ]
  }, {
    "href" : "https://img.abctruyen.xyz/uploads/19088/chuong-89/30.jpg",
    "type" : "image/jpeg",
    "bitrate" : 0,
    "duration" : 0,
    "title" : null,
    "properties" : null,
    "alternate" : [ {
      "href" : "https://i2.wp.com/img.abctruyen.xyz/uploads/19088/chuong-89/30.jpg",
      "type" : "image/jpeg",
      "bitrate" : 0,
      "duration" : 0,
      "title" : null,
      "properties" : null,
      "alternate" : null
    } ]
  }, {
    "href" : "https://img.abctruyen.xyz/uploads/19088/chuong-89/31.jpg",
    "type" : "image/jpeg",
    "bitrate" : 0,
    "duration" : 0,
    "title" : null,
    "properties" : null,
    "alternate" : [ {
      "href" : "https://i2.wp.com/img.abctruyen.xyz/uploads/19088/chuong-89/31.jpg",
      "type" : "image/jpeg",
      "bitrate" : 0,
      "duration" : 0,
      "title" : null,
      "properties" : null,
      "alternate" : null
    } ]
  }, {
    "href" : "https://img.abctruyen.xyz/uploads/19088/chuong-89/32.jpg",
    "type" : "image/jpeg",
    "bitrate" : 0,
    "duration" : 0,
    "title" : null,
    "properties" : null,
    "alternate" : [ {
      "href" : "https://i2.wp.com/img.abctruyen.xyz/uploads/19088/chuong-89/32.jpg",
      "type" : "image/jpeg",
      "bitrate" : 0,
      "duration" : 0,
      "title" : null,
      "properties" : null,
      "alternate" : null
    } ]
  }, {
    "href" : "https://img.abctruyen.xyz/uploads/19088/chuong-89/33.jpg",
    "type" : "image/jpeg",
    "bitrate" : 0,
    "duration" : 0,
    "title" : null,
    "properties" : null,
    "alternate" : [ {
      "href" : "https://i2.wp.com/img.abctruyen.xyz/uploads/19088/chuong-89/33.jpg",
      "type" : "image/jpeg",
      "bitrate" : 0,
      "duration" : 0,
      "title" : null,
      "properties" : null,
      "alternate" : null
    } ]
  }, {
    "href" : "https://img.abctruyen.xyz/uploads/19088/chuong-89/34.jpg",
    "type" : "image/jpeg",
    "bitrate" : 0,
    "duration" : 0,
    "title" : null,
    "properties" : null,
    "alternate" : [ {
      "href" : "https://i2.wp.com/img.abctruyen.xyz/uploads/19088/chuong-89/34.jpg",
      "type" : "image/jpeg",
      "bitrate" : 0,
      "duration" : 0,
      "title" : null,
      "properties" : null,
      "alternate" : null
    } ]
  }, {
    "href" : "https://img.abctruyen.xyz/uploads/19088/chuong-89/35.jpg",
    "type" : "image/jpeg",
    "bitrate" : 0,
    "duration" : 0,
    "title" : null,
    "properties" : null,
    "alternate" : [ {
      "href" : "https://i2.wp.com/img.abctruyen.xyz/uploads/19088/chuong-89/35.jpg",
      "type" : "image/jpeg",
      "bitrate" : 0,
      "duration" : 0,
      "title" : null,
      "properties" : null,
      "alternate" : null
    } ]
  }, {
    "href" : "https://img.abctruyen.xyz/uploads/19088/chuong-89/36.jpg",
    "type" : "image/jpeg",
    "bitrate" : 0,
    "duration" : 0,
    "title" : null,
    "properties" : null,
    "alternate" : [ {
      "href" : "https://i2.wp.com/img.abctruyen.xyz/uploads/19088/chuong-89/36.jpg",
      "type" : "image/jpeg",
      "bitrate" : 0,
      "duration" : 0,
      "title" : null,
      "properties" : null,
      "alternate" : null
    } ]
  }, {
    "href" : "https://img.abctruyen.xyz/uploads/19088/chuong-89/37.jpg",
    "type" : "image/jpeg",
    "bitrate" : 0,
    "duration" : 0,
    "title" : null,
    "properties" : null,
    "alternate" : [ {
      "href" : "https://i2.wp.com/img.abctruyen.xyz/uploads/19088/chuong-89/37.jpg",
      "type" : "image/jpeg",
      "bitrate" : 0,
      "duration" : 0,
      "title" : null,
      "properties" : null,
      "alternate" : null
    } ]
  }, {
    "href" : "https://img.abctruyen.xyz/uploads/19088/chuong-89/38.jpg",
    "type" : "image/jpeg",
    "bitrate" : 0,
    "duration" : 0,
    "title" : null,
    "properties" : null,
    "alternate" : [ {
      "href" : "https://i2.wp.com/img.abctruyen.xyz/uploads/19088/chuong-89/38.jpg",
      "type" : "image/jpeg",
      "bitrate" : 0,
      "duration" : 0,
      "title" : null,
      "properties" : null,
      "alternate" : null
    } ]
  }, {
    "href" : "https://img.abctruyen.xyz/uploads/19088/chuong-89/39.jpg",
    "type" : "image/jpeg",
    "bitrate" : 0,
    "duration" : 0,
    "title" : null,
    "properties" : null,
    "alternate" : [ {
      "href" : "https://i2.wp.com/img.abctruyen.xyz/uploads/19088/chuong-89/39.jpg",
      "type" : "image/jpeg",
      "bitrate" : 0,
      "duration" : 0,
      "title" : null,
      "properties" : null,
      "alternate" : null
    } ]
  }, {
    "href" : "https://img.abctruyen.xyz/uploads/19088/chuong-89/40.jpg",
    "type" : "image/jpeg",
    "bitrate" : 0,
    "duration" : 0,
    "title" : null,
    "properties" : null,
    "alternate" : [ {
      "href" : "https://i2.wp.com/img.abctruyen.xyz/uploads/19088/chuong-89/40.jpg",
      "type" : "image/jpeg",
      "bitrate" : 0,
      "duration" : 0,
      "title" : null,
      "properties" : null,
      "alternate" : null
    } ]
  }, {
    "href" : "https://img.abctruyen.xyz/uploads/19088/chuong-89/41.jpg",
    "type" : "image/jpeg",
    "bitrate" : 0,
    "duration" : 0,
    "title" : null,
    "properties" : null,
    "alternate" : [ {
      "href" : "https://i2.wp.com/img.abctruyen.xyz/uploads/19088/chuong-89/41.jpg",
      "type" : "image/jpeg",
      "bitrate" : 0,
      "duration" : 0,
      "title" : null,
      "properties" : null,
      "alternate" : null
    } ]
  }, {
    "href" : "https://img.abctruyen.xyz/uploads/19088/chuong-89/42.jpg",
    "type" : "image/jpeg",
    "bitrate" : 0,
    "duration" : 0,
    "title" : null,
    "properties" : null,
    "alternate" : [ {
      "href" : "https://i2.wp.com/img.abctruyen.xyz/uploads/19088/chuong-89/42.jpg",
      "type" : "image/jpeg",
      "bitrate" : 0,
      "duration" : 0,
      "title" : null,
      "properties" : null,
      "alternate" : null
    } ]
  }, {
    "href" : "https://img.abctruyen.xyz/uploads/19088/chuong-89/43.jpg",
    "type" : "image/jpeg",
    "bitrate" : 0,
    "duration" : 0,
    "title" : null,
    "properties" : null,
    "alternate" : [ {
      "href" : "https://i2.wp.com/img.abctruyen.xyz/uploads/19088/chuong-89/43.jpg",
      "type" : "image/jpeg",
      "bitrate" : 0,
      "duration" : 0,
      "title" : null,
      "properties" : null,
      "alternate" : null
    } ]
  }, {
    "href" : "https://img.abctruyen.xyz/uploads/19088/chuong-89/44.jpg",
    "type" : "image/jpeg",
    "bitrate" : 0,
    "duration" : 0,
    "title" : null,
    "properties" : null,
    "alternate" : [ {
      "href" : "https://i2.wp.com/img.abctruyen.xyz/uploads/19088/chuong-89/44.jpg",
      "type" : "image/jpeg",
      "bitrate" : 0,
      "duration" : 0,
      "title" : null,
      "properties" : null,
      "alternate" : null
    } ]
  }, {
    "href" : "https://img.abctruyen.xyz/uploads/19088/chuong-89/45.jpg",
    "type" : "image/jpeg",
    "bitrate" : 0,
    "duration" : 0,
    "title" : null,
    "properties" : null,
    "alternate" : [ {
      "href" : "https://i2.wp.com/img.abctruyen.xyz/uploads/19088/chuong-89/45.jpg",
      "type" : "image/jpeg",
      "bitrate" : 0,
      "duration" : 0,
      "title" : null,
      "properties" : null,
      "alternate" : null
    } ]
  }, {
    "href" : "https://img.abctruyen.xyz/uploads/19088/chuong-89/46.jpg",
    "type" : "image/jpeg",
    "bitrate" : 0,
    "duration" : 0,
    "title" : null,
    "properties" : null,
    "alternate" : [ {
      "href" : "https://i2.wp.com/img.abctruyen.xyz/uploads/19088/chuong-89/46.jpg",
      "type" : "image/jpeg",
      "bitrate" : 0,
      "duration" : 0,
      "title" : null,
      "properties" : null,
      "alternate" : null
    } ]
  }, {
    "href" : "https://img.abctruyen.xyz/uploads/19088/chuong-89/47.jpg",
    "type" : "image/jpeg",
    "bitrate" : 0,
    "duration" : 0,
    "title" : null,
    "properties" : null,
    "alternate" : [ {
      "href" : "https://i2.wp.com/img.abctruyen.xyz/uploads/19088/chuong-89/47.jpg",
      "type" : "image/jpeg",
      "bitrate" : 0,
      "duration" : 0,
      "title" : null,
      "properties" : null,
      "alternate" : null
    } ]
  }, {
    "href" : "https://img.abctruyen.xyz/uploads/19088/chuong-89/48.jpg",
    "type" : "image/jpeg",
    "bitrate" : 0,
    "duration" : 0,
    "title" : null,
    "properties" : null,
    "alternate" : [ {
      "href" : "https://i2.wp.com/img.abctruyen.xyz/uploads/19088/chuong-89/48.jpg",
      "type" : "image/jpeg",
      "bitrate" : 0,
      "duration" : 0,
      "title" : null,
      "properties" : null,
      "alternate" : null
    } ]
  }, {
    "href" : "https://img.abctruyen.xyz/uploads/19088/chuong-89/49.jpg",
    "type" : "image/jpeg",
    "bitrate" : 0,
    "duration" : 0,
    "title" : null,
    "properties" : null,
    "alternate" : [ {
      "href" : "https://i2.wp.com/img.abctruyen.xyz/uploads/19088/chuong-89/49.jpg",
      "type" : "image/jpeg",
      "bitrate" : 0,
      "duration" : 0,
      "title" : null,
      "properties" : null,
      "alternate" : null
    } ]
  }, {
    "href" : "https://img.abctruyen.xyz/uploads/19088/chuong-89/50.jpg",
    "type" : "image/jpeg",
    "bitrate" : 0,
    "duration" : 0,
    "title" : null,
    "properties" : null,
    "alternate" : [ {
      "href" : "https://i2.wp.com/img.abctruyen.xyz/uploads/19088/chuong-89/50.jpg",
      "type" : "image/jpeg",
      "bitrate" : 0,
      "duration" : 0,
      "title" : null,
      "properties" : null,
      "alternate" : null
    } ]
  }, {
    "href" : "https://img.abctruyen.xyz/uploads/19088/chuong-89/51.jpg",
    "type" : "image/jpeg",
    "bitrate" : 0,
    "duration" : 0,
    "title" : null,
    "properties" : null,
    "alternate" : [ {
      "href" : "https://i2.wp.com/img.abctruyen.xyz/uploads/19088/chuong-89/51.jpg",
      "type" : "image/jpeg",
      "bitrate" : 0,
      "duration" : 0,
      "title" : null,
      "properties" : null,
      "alternate" : null
    } ]
  }, {
    "href" : "https://img.abctruyen.xyz/uploads/19088/chuong-89/52.jpg",
    "type" : "image/jpeg",
    "bitrate" : 0,
    "duration" : 0,
    "title" : null,
    "properties" : null,
    "alternate" : [ {
      "href" : "https://i2.wp.com/img.abctruyen.xyz/uploads/19088/chuong-89/52.jpg",
      "type" : "image/jpeg",
      "bitrate" : 0,
      "duration" : 0,
      "title" : null,
      "properties" : null,
      "alternate" : null
    } ]
  }, {
    "href" : "https://img.abctruyen.xyz/uploads/19088/chuong-89/53.jpg",
    "type" : "image/jpeg",
    "bitrate" : 0,
    "duration" : 0,
    "title" : null,
    "properties" : null,
    "alternate" : [ {
      "href" : "https://i2.wp.com/img.abctruyen.xyz/uploads/19088/chuong-89/53.jpg",
      "type" : "image/jpeg",
      "bitrate" : 0,
      "duration" : 0,
      "title" : null,
      "properties" : null,
      "alternate" : null
    } ]
  }, {
    "href" : "https://img.abctruyen.xyz/uploads/19088/chuong-89/54.jpg",
    "type" : "image/jpeg",
    "bitrate" : 0,
    "duration" : 0,
    "title" : null,
    "properties" : null,
    "alternate" : [ {
      "href" : "https://i2.wp.com/img.abctruyen.xyz/uploads/19088/chuong-89/54.jpg",
      "type" : "image/jpeg",
      "bitrate" : 0,
      "duration" : 0,
      "title" : null,
      "properties" : null,
      "alternate" : null
    } ]
  }, {
    "href" : "https://img.abctruyen.xyz/uploads/19088/chuong-89/55.jpg",
    "type" : "image/jpeg",
    "bitrate" : 0,
    "duration" : 0,
    "title" : null,
    "properties" : null,
    "alternate" : [ {
      "href" : "https://i2.wp.com/img.abctruyen.xyz/uploads/19088/chuong-89/55.jpg",
      "type" : "image/jpeg",
      "bitrate" : 0,
      "duration" : 0,
      "title" : null,
      "properties" : null,
      "alternate" : null
    } ]
  }, {
    "href" : "https://img.abctruyen.xyz/uploads/19088/chuong-89/56.jpg",
    "type" : "image/jpeg",
    "bitrate" : 0,
    "duration" : 0,
    "title" : null,
    "properties" : null,
    "alternate" : [ {
      "href" : "https://i2.wp.com/img.abctruyen.xyz/uploads/19088/chuong-89/56.jpg",
      "type" : "image/jpeg",
      "bitrate" : 0,
      "duration" : 0,
      "title" : null,
      "properties" : null,
      "alternate" : null
    } ]
  }, {
    "href" : "https://img.abctruyen.xyz/uploads/19088/chuong-89/57.jpg",
    "type" : "image/jpeg",
    "bitrate" : 0,
    "duration" : 0,
    "title" : null,
    "properties" : null,
    "alternate" : [ {
      "href" : "https://i2.wp.com/img.abctruyen.xyz/uploads/19088/chuong-89/57.jpg",
      "type" : "image/jpeg",
      "bitrate" : 0,
      "duration" : 0,
      "title" : null,
      "properties" : null,
      "alternate" : null
    } ]
  }, {
    "href" : "https://img.abctruyen.xyz/uploads/19088/chuong-89/58.jpg",
    "type" : "image/jpeg",
    "bitrate" : 0,
    "duration" : 0,
    "title" : null,
    "properties" : null,
    "alternate" : [ {
      "href" : "https://i2.wp.com/img.abctruyen.xyz/uploads/19088/chuong-89/58.jpg",
      "type" : "image/jpeg",
      "bitrate" : 0,
      "duration" : 0,
      "title" : null,
      "properties" : null,
      "alternate" : null
    } ]
  }, {
    "href" : "https://img.abctruyen.xyz/uploads/19088/chuong-89/59.jpg",
    "type" : "image/jpeg",
    "bitrate" : 0,
    "duration" : 0,
    "title" : null,
    "properties" : null,
    "alternate" : [ {
      "href" : "https://i2.wp.com/img.abctruyen.xyz/uploads/19088/chuong-89/59.jpg",
      "type" : "image/jpeg",
      "bitrate" : 0,
      "duration" : 0,
      "title" : null,
      "properties" : null,
      "alternate" : null
    } ]
  }, {
    "href" : "https://img.abctruyen.xyz/uploads/19088/chuong-89/60.jpg",
    "type" : "image/jpeg",
    "bitrate" : 0,
    "duration" : 0,
    "title" : null,
    "properties" : null,
    "alternate" : [ {
      "href" : "https://i2.wp.com/img.abctruyen.xyz/uploads/19088/chuong-89/60.jpg",
      "type" : "image/jpeg",
      "bitrate" : 0,
      "duration" : 0,
      "title" : null,
      "properties" : null,
      "alternate" : null
    } ]
  }, {
    "href" : "https://img.abctruyen.xyz/uploads/19088/chuong-89/61.jpg",
    "type" : "image/jpeg",
    "bitrate" : 0,
    "duration" : 0,
    "title" : null,
    "properties" : null,
    "alternate" : [ {
      "href" : "https://i2.wp.com/img.abctruyen.xyz/uploads/19088/chuong-89/61.jpg",
      "type" : "image/jpeg",
      "bitrate" : 0,
      "duration" : 0,
      "title" : null,
      "properties" : null,
      "alternate" : null
    } ]
  }, {
    "href" : "https://img.abctruyen.xyz/uploads/19088/chuong-89/62.jpg",
    "type" : "image/jpeg",
    "bitrate" : 0,
    "duration" : 0,
    "title" : null,
    "properties" : null,
    "alternate" : [ {
      "href" : "https://i2.wp.com/img.abctruyen.xyz/uploads/19088/chuong-89/62.jpg",
      "type" : "image/jpeg",
      "bitrate" : 0,
      "duration" : 0,
      "title" : null,
      "properties" : null,
      "alternate" : null
    } ]
  }, {
    "href" : "https://img.abctruyen.xyz/uploads/19088/chuong-89/63.jpg",
    "type" : "image/jpeg",
    "bitrate" : 0,
    "duration" : 0,
    "title" : null,
    "properties" : null,
    "alternate" : [ {
      "href" : "https://i2.wp.com/img.abctruyen.xyz/uploads/19088/chuong-89/63.jpg",
      "type" : "image/jpeg",
      "bitrate" : 0,
      "duration" : 0,
      "title" : null,
      "properties" : null,
      "alternate" : null
    } ]
  }, {
    "href" : "https://img.abctruyen.xyz/uploads/19088/chuong-89/64.jpg",
    "type" : "image/jpeg",
    "bitrate" : 0,
    "duration" : 0,
    "title" : null,
    "properties" : null,
    "alternate" : [ {
      "href" : "https://i2.wp.com/img.abctruyen.xyz/uploads/19088/chuong-89/64.jpg",
      "type" : "image/jpeg",
      "bitrate" : 0,
      "duration" : 0,
      "title" : null,
      "properties" : null,
      "alternate" : null
    } ]
  }, {
    "href" : "https://img.abctruyen.xyz/uploads/19088/chuong-89/65.jpg",
    "type" : "image/jpeg",
    "bitrate" : 0,
    "duration" : 0,
    "title" : null,
    "properties" : null,
    "alternate" : [ {
      "href" : "https://i2.wp.com/img.abctruyen.xyz/uploads/19088/chuong-89/65.jpg",
      "type" : "image/jpeg",
      "bitrate" : 0,
      "duration" : 0,
      "title" : null,
      "properties" : null,
      "alternate" : null
    } ]
  }, {
    "href" : "https://img.abctruyen.xyz/uploads/19088/chuong-89/66.jpg",
    "type" : "image/jpeg",
    "bitrate" : 0,
    "duration" : 0,
    "title" : null,
    "properties" : null,
    "alternate" : [ {
      "href" : "https://i2.wp.com/img.abctruyen.xyz/uploads/19088/chuong-89/66.jpg",
      "type" : "image/jpeg",
      "bitrate" : 0,
      "duration" : 0,
      "title" : null,
      "properties" : null,
      "alternate" : null
    } ]
  }, {
    "href" : "https://img.abctruyen.xyz/uploads/19088/chuong-89/67.jpg",
    "type" : "image/jpeg",
    "bitrate" : 0,
    "duration" : 0,
    "title" : null,
    "properties" : null,
    "alternate" : [ {
      "href" : "https://i2.wp.com/img.abctruyen.xyz/uploads/19088/chuong-89/67.jpg",
      "type" : "image/jpeg",
      "bitrate" : 0,
      "duration" : 0,
      "title" : null,
      "properties" : null,
      "alternate" : null
    } ]
  }, {
    "href" : "https://img.abctruyen.xyz/uploads/19088/chuong-89/68.jpg",
    "type" : "image/jpeg",
    "bitrate" : 0,
    "duration" : 0,
    "title" : null,
    "properties" : null,
    "alternate" : [ {
      "href" : "https://i2.wp.com/img.abctruyen.xyz/uploads/19088/chuong-89/68.jpg",
      "type" : "image/jpeg",
      "bitrate" : 0,
      "duration" : 0,
      "title" : null,
      "properties" : null,
      "alternate" : null
    } ]
  }, {
    "href" : "https://img.abctruyen.xyz/uploads/19088/chuong-89/69.jpg",
    "type" : "image/jpeg",
    "bitrate" : 0,
    "duration" : 0,
    "title" : null,
    "properties" : null,
    "alternate" : [ {
      "href" : "https://i2.wp.com/img.abctruyen.xyz/uploads/19088/chuong-89/69.jpg",
      "type" : "image/jpeg",
      "bitrate" : 0,
      "duration" : 0,
      "title" : null,
      "properties" : null,
      "alternate" : null
    } ]
  }, {
    "href" : "https://img.abctruyen.xyz/uploads/19088/chuong-89/70.jpg",
    "type" : "image/jpeg",
    "bitrate" : 0,
    "duration" : 0,
    "title" : null,
    "properties" : null,
    "alternate" : [ {
      "href" : "https://i2.wp.com/img.abctruyen.xyz/uploads/19088/chuong-89/70.jpg",
      "type" : "image/jpeg",
      "bitrate" : 0,
      "duration" : 0,
      "title" : null,
      "properties" : null,
      "alternate" : null
    } ]
  }, {
    "href" : "https://img.abctruyen.xyz/uploads/19088/chuong-89/71.jpg",
    "type" : "image/jpeg",
    "bitrate" : 0,
    "duration" : 0,
    "title" : null,
    "properties" : null,
    "alternate" : [ {
      "href" : "https://i2.wp.com/img.abctruyen.xyz/uploads/19088/chuong-89/71.jpg",
      "type" : "image/jpeg",
      "bitrate" : 0,
      "duration" : 0,
      "title" : null,
      "properties" : null,
      "alternate" : null
    } ]
  }, {
    "href" : "https://img.abctruyen.xyz/uploads/19088/chuong-89/72.jpg",
    "type" : "image/jpeg",
    "bitrate" : 0,
    "duration" : 0,
    "title" : null,
    "properties" : null,
    "alternate" : [ {
      "href" : "https://i2.wp.com/img.abctruyen.xyz/uploads/19088/chuong-89/72.jpg",
      "type" : "image/jpeg",
      "bitrate" : 0,
      "duration" : 0,
      "title" : null,
      "properties" : null,
      "alternate" : null
    } ]
  }, {
    "href" : "https://img.abctruyen.xyz/uploads/19088/chuong-89/73.jpg",
    "type" : "image/jpeg",
    "bitrate" : 0,
    "duration" : 0,
    "title" : null,
    "properties" : null,
    "alternate" : [ {
      "href" : "https://i2.wp.com/img.abctruyen.xyz/uploads/19088/chuong-89/73.jpg",
      "type" : "image/jpeg",
      "bitrate" : 0,
      "duration" : 0,
      "title" : null,
      "properties" : null,
      "alternate" : null
    } ]
  }, {
    "href" : "https://img.abctruyen.xyz/uploads/19088/chuong-89/74.jpg",
    "type" : "image/jpeg",
    "bitrate" : 0,
    "duration" : 0,
    "title" : null,
    "properties" : null,
    "alternate" : [ {
      "href" : "https://i2.wp.com/img.abctruyen.xyz/uploads/19088/chuong-89/74.jpg",
      "type" : "image/jpeg",
      "bitrate" : 0,
      "duration" : 0,
      "title" : null,
      "properties" : null,
      "alternate" : null
    } ]
  }, {
    "href" : "https://img.abctruyen.xyz/uploads/19088/chuong-89/75.jpg",
    "type" : "image/jpeg",
    "bitrate" : 0,
    "duration" : 0,
    "title" : null,
    "properties" : null,
    "alternate" : [ {
      "href" : "https://i2.wp.com/img.abctruyen.xyz/uploads/19088/chuong-89/75.jpg",
      "type" : "image/jpeg",
      "bitrate" : 0,
      "duration" : 0,
      "title" : null,
      "properties" : null,
      "alternate" : null
    } ]
  }, {
    "href" : "https://img.abctruyen.xyz/uploads/19088/chuong-89/76.jpg",
    "type" : "image/jpeg",
    "bitrate" : 0,
    "duration" : 0,
    "title" : null,
    "properties" : null,
    "alternate" : [ {
      "href" : "https://i2.wp.com/img.abctruyen.xyz/uploads/19088/chuong-89/76.jpg",
      "type" : "image/jpeg",
      "bitrate" : 0,
      "duration" : 0,
      "title" : null,
      "properties" : null,
      "alternate" : null
    } ]
  }, {
    "href" : "https://img.abctruyen.xyz/uploads/19088/chuong-89/77.jpg",
    "type" : "image/jpeg",
    "bitrate" : 0,
    "duration" : 0,
    "title" : null,
    "properties" : null,
    "alternate" : [ {
      "href" : "https://i2.wp.com/img.abctruyen.xyz/uploads/19088/chuong-89/77.jpg",
      "type" : "image/jpeg",
      "bitrate" : 0,
      "duration" : 0,
      "title" : null,
      "properties" : null,
      "alternate" : null
    } ]
  }, {
    "href" : "https://img.abctruyen.xyz/uploads/19088/chuong-89/78.jpg",
    "type" : "image/jpeg",
    "bitrate" : 0,
    "duration" : 0,
    "title" : null,
    "properties" : null,
    "alternate" : [ {
      "href" : "https://i2.wp.com/img.abctruyen.xyz/uploads/19088/chuong-89/78.jpg",
      "type" : "image/jpeg",
      "bitrate" : 0,
      "duration" : 0,
      "title" : null,
      "properties" : null,
      "alternate" : null
    } ]
  }, {
    "href" : "https://img.abctruyen.xyz/uploads/19088/chuong-89/79.jpg",
    "type" : "image/jpeg",
    "bitrate" : 0,
    "duration" : 0,
    "title" : null,
    "properties" : null,
    "alternate" : [ {
      "href" : "https://i2.wp.com/img.abctruyen.xyz/uploads/19088/chuong-89/79.jpg",
      "type" : "image/jpeg",
      "bitrate" : 0,
      "duration" : 0,
      "title" : null,
      "properties" : null,
      "alternate" : null
    } ]
  }, {
    "href" : "https://img.abctruyen.xyz/uploads/19088/chuong-89/80.jpg",
    "type" : "image/jpeg",
    "bitrate" : 0,
    "duration" : 0,
    "title" : null,
    "properties" : null,
    "alternate" : [ {
      "href" : "https://i2.wp.com/img.abctruyen.xyz/uploads/19088/chuong-89/80.jpg",
      "type" : "image/jpeg",
      "bitrate" : 0,
      "duration" : 0,
      "title" : null,
      "properties" : null,
      "alternate" : null
    } ]
  }, {
    "href" : "https://img.abctruyen.xyz/uploads/19088/chuong-89/81.jpg",
    "type" : "image/jpeg",
    "bitrate" : 0,
    "duration" : 0,
    "title" : null,
    "properties" : null,
    "alternate" : [ {
      "href" : "https://i2.wp.com/img.abctruyen.xyz/uploads/19088/chuong-89/81.jpg",
      "type" : "image/jpeg",
      "bitrate" : 0,
      "duration" : 0,
      "title" : null,
      "properties" : null,
      "alternate" : null
    } ]
  }, {
    "href" : "https://img.abctruyen.xyz/uploads/19088/chuong-89/82.jpg",
    "type" : "image/jpeg",
    "bitrate" : 0,
    "duration" : 0,
    "title" : null,
    "properties" : null,
    "alternate" : [ {
      "href" : "https://i2.wp.com/img.abctruyen.xyz/uploads/19088/chuong-89/82.jpg",
      "type" : "image/jpeg",
      "bitrate" : 0,
      "duration" : 0,
      "title" : null,
      "properties" : null,
      "alternate" : null
    } ]
  }, {
    "href" : "https://img.abctruyen.xyz/uploads/19088/chuong-89/83.jpg",
    "type" : "image/jpeg",
    "bitrate" : 0,
    "duration" : 0,
    "title" : null,
    "properties" : null,
    "alternate" : [ {
      "href" : "https://i2.wp.com/img.abctruyen.xyz/uploads/19088/chuong-89/83.jpg",
      "type" : "image/jpeg",
      "bitrate" : 0,
      "duration" : 0,
      "title" : null,
      "properties" : null,
      "alternate" : null
    } ]
  }, {
    "href" : "https://img.abctruyen.xyz/uploads/19088/chuong-89/84.jpg",
    "type" : "image/jpeg",
    "bitrate" : 0,
    "duration" : 0,
    "title" : null,
    "properties" : null,
    "alternate" : [ {
      "href" : "https://i2.wp.com/img.abctruyen.xyz/uploads/19088/chuong-89/84.jpg",
      "type" : "image/jpeg",
      "bitrate" : 0,
      "duration" : 0,
      "title" : null,
      "properties" : null,
      "alternate" : null
    } ]
  }, {
    "href" : "https://img.abctruyen.xyz/uploads/19088/chuong-89/85.jpg",
    "type" : "image/jpeg",
    "bitrate" : 0,
    "duration" : 0,
    "title" : null,
    "properties" : null,
    "alternate" : [ {
      "href" : "https://i2.wp.com/img.abctruyen.xyz/uploads/19088/chuong-89/85.jpg",
      "type" : "image/jpeg",
      "bitrate" : 0,
      "duration" : 0,
      "title" : null,
      "properties" : null,
      "alternate" : null
    } ]
  }, {
    "href" : "https://img.abctruyen.xyz/uploads/19088/chuong-89/86.jpg",
    "type" : "image/jpeg",
    "bitrate" : 0,
    "duration" : 0,
    "title" : null,
    "properties" : null,
    "alternate" : [ {
      "href" : "https://i2.wp.com/img.abctruyen.xyz/uploads/19088/chuong-89/86.jpg",
      "type" : "image/jpeg",
      "bitrate" : 0,
      "duration" : 0,
      "title" : null,
      "properties" : null,
      "alternate" : null
    } ]
  }, {
    "href" : "https://img.abctruyen.xyz/uploads/19088/chuong-89/87.jpg",
    "type" : "image/jpeg",
    "bitrate" : 0,
    "duration" : 0,
    "title" : null,
    "properties" : null,
    "alternate" : [ {
      "href" : "https://i2.wp.com/img.abctruyen.xyz/uploads/19088/chuong-89/87.jpg",
      "type" : "image/jpeg",
      "bitrate" : 0,
      "duration" : 0,
      "title" : null,
      "properties" : null,
      "alternate" : null
    } ]
  }, {
    "href" : "https://img.abctruyen.xyz/uploads/19088/chuong-89/88.jpg",
    "type" : "image/jpeg",
    "bitrate" : 0,
    "duration" : 0,
    "title" : null,
    "properties" : null,
    "alternate" : [ {
      "href" : "https://i2.wp.com/img.abctruyen.xyz/uploads/19088/chuong-89/88.jpg",
      "type" : "image/jpeg",
      "bitrate" : 0,
      "duration" : 0,
      "title" : null,
      "properties" : null,
      "alternate" : null
    } ]
  }, {
    "href" : "https://img.abctruyen.xyz/uploads/19088/chuong-89/89.jpg",
    "type" : "image/jpeg",
    "bitrate" : 0,
    "duration" : 0,
    "title" : null,
    "properties" : null,
    "alternate" : [ {
      "href" : "https://i2.wp.com/img.abctruyen.xyz/uploads/19088/chuong-89/89.jpg",
      "type" : "image/jpeg",
      "bitrate" : 0,
      "duration" : 0,
      "title" : null,
      "properties" : null,
      "alternate" : null
    } ]
  }, {
    "href" : "https://img.abctruyen.xyz/uploads/19088/chuong-89/90.jpg",
    "type" : "image/jpeg",
    "bitrate" : 0,
    "duration" : 0,
    "title" : null,
    "properties" : null,
    "alternate" : [ {
      "href" : "https://i2.wp.com/img.abctruyen.xyz/uploads/19088/chuong-89/90.jpg",
      "type" : "image/jpeg",
      "bitrate" : 0,
      "duration" : 0,
      "title" : null,
      "properties" : null,
      "alternate" : null
    } ]
  }, {
    "href" : "https://img.abctruyen.xyz/uploads/19088/chuong-89/91.jpg",
    "type" : "image/jpeg",
    "bitrate" : 0,
    "duration" : 0,
    "title" : null,
    "properties" : null,
    "alternate" : [ {
      "href" : "https://i2.wp.com/img.abctruyen.xyz/uploads/19088/chuong-89/91.jpg",
      "type" : "image/jpeg",
      "bitrate" : 0,
      "duration" : 0,
      "title" : null,
      "properties" : null,
      "alternate" : null
    } ]
  }, {
    "href" : "https://img.abctruyen.xyz/uploads/19088/chuong-89/92.jpg",
    "type" : "image/jpeg",
    "bitrate" : 0,
    "duration" : 0,
    "title" : null,
    "properties" : null,
    "alternate" : [ {
      "href" : "https://i2.wp.com/img.abctruyen.xyz/uploads/19088/chuong-89/92.jpg",
      "type" : "image/jpeg",
      "bitrate" : 0,
      "duration" : 0,
      "title" : null,
      "properties" : null,
      "alternate" : null
    } ]
  }, {
    "href" : "https://img.abctruyen.xyz/uploads/19088/chuong-89/93.jpg",
    "type" : "image/jpeg",
    "bitrate" : 0,
    "duration" : 0,
    "title" : null,
    "properties" : null,
    "alternate" : [ {
      "href" : "https://i2.wp.com/img.abctruyen.xyz/uploads/19088/chuong-89/93.jpg",
      "type" : "image/jpeg",
      "bitrate" : 0,
      "duration" : 0,
      "title" : null,
      "properties" : null,
      "alternate" : null
    } ]
  }, {
    "href" : "https://img.abctruyen.xyz/uploads/19088/chuong-89/94.jpg",
    "type" : "image/jpeg",
    "bitrate" : 0,
    "duration" : 0,
    "title" : null,
    "properties" : null,
    "alternate" : [ {
      "href" : "https://i2.wp.com/img.abctruyen.xyz/uploads/19088/chuong-89/94.jpg",
      "type" : "image/jpeg",
      "bitrate" : 0,
      "duration" : 0,
      "title" : null,
      "properties" : null,
      "alternate" : null
    } ]
  }, {
    "href" : "https://img.abctruyen.xyz/uploads/19088/chuong-89/95.jpg",
    "type" : "image/jpeg",
    "bitrate" : 0,
    "duration" : 0,
    "title" : null,
    "properties" : null,
    "alternate" : [ {
      "href" : "https://i2.wp.com/img.abctruyen.xyz/uploads/19088/chuong-89/95.jpg",
      "type" : "image/jpeg",
      "bitrate" : 0,
      "duration" : 0,
      "title" : null,
      "properties" : null,
      "alternate" : null
    } ]
  }, {
    "href" : "https://img.abctruyen.xyz/uploads/19088/chuong-89/96.jpg",
    "type" : "image/jpeg",
    "bitrate" : 0,
    "duration" : 0,
    "title" : null,
    "properties" : null,
    "alternate" : [ {
      "href" : "https://i2.wp.com/img.abctruyen.xyz/uploads/19088/chuong-89/96.jpg",
      "type" : "image/jpeg",
      "bitrate" : 0,
      "duration" : 0,
      "title" : null,
      "properties" : null,
      "alternate" : null
    } ]
  }, {
    "href" : "https://img.abctruyen.xyz/uploads/19088/chuong-89/97.jpg",
    "type" : "image/jpeg",
    "bitrate" : 0,
    "duration" : 0,
    "title" : null,
    "properties" : null,
    "alternate" : [ {
      "href" : "https://i2.wp.com/img.abctruyen.xyz/uploads/19088/chuong-89/97.jpg",
      "type" : "image/jpeg",
      "bitrate" : 0,
      "duration" : 0,
      "title" : null,
      "properties" : null,
      "alternate" : null
    } ]
  }, {
    "href" : "https://img.abctruyen.xyz/uploads/19088/chuong-89/98.jpg",
    "type" : "image/jpeg",
    "bitrate" : 0,
    "duration" : 0,
    "title" : null,
    "properties" : null,
    "alternate" : [ {
      "href" : "https://i2.wp.com/img.abctruyen.xyz/uploads/19088/chuong-89/98.jpg",
      "type" : "image/jpeg",
      "bitrate" : 0,
      "duration" : 0,
      "title" : null,
      "properties" : null,
      "alternate" : null
    } ]
  }, {
    "href" : "https://img.abctruyen.xyz/uploads/19088/chuong-89/99.jpg",
    "type" : "image/jpeg",
    "bitrate" : 0,
    "duration" : 0,
    "title" : null,
    "properties" : null,
    "alternate" : [ {
      "href" : "https://i2.wp.com/img.abctruyen.xyz/uploads/19088/chuong-89/99.jpg",
      "type" : "image/jpeg",
      "bitrate" : 0,
      "duration" : 0,
      "title" : null,
      "properties" : null,
      "alternate" : null
    } ]
  }, {
    "href" : "https://img.abctruyen.xyz/uploads/19088/chuong-89/100.jpg",
    "type" : "image/jpeg",
    "bitrate" : 0,
    "duration" : 0,
    "title" : null,
    "properties" : null,
    "alternate" : [ {
      "href" : "https://i2.wp.com/img.abctruyen.xyz/uploads/19088/chuong-89/100.jpg",
      "type" : "image/jpeg",
      "bitrate" : 0,
      "duration" : 0,
      "title" : null,
      "properties" : null,
      "alternate" : null
    } ]
  }, {
    "href" : "https://img.abctruyen.xyz/uploads/19088/chuong-89/101.jpg",
    "type" : "image/jpeg",
    "bitrate" : 0,
    "duration" : 0,
    "title" : null,
    "properties" : null,
    "alternate" : [ {
      "href" : "https://i2.wp.com/img.abctruyen.xyz/uploads/19088/chuong-89/101.jpg",
      "type" : "image/jpeg",
      "bitrate" : 0,
      "duration" : 0,
      "title" : null,
      "properties" : null,
      "alternate" : null
    } ]
  }, {
    "href" : "https://img.abctruyen.xyz/uploads/19088/chuong-89/102.jpg",
    "type" : "image/jpeg",
    "bitrate" : 0,
    "duration" : 0,
    "title" : null,
    "properties" : null,
    "alternate" : [ {
      "href" : "https://i2.wp.com/img.abctruyen.xyz/uploads/19088/chuong-89/102.jpg",
      "type" : "image/jpeg",
      "bitrate" : 0,
      "duration" : 0,
      "title" : null,
      "properties" : null,
      "alternate" : null
    } ]
  }, {
    "href" : "https://img.abctruyen.xyz/uploads/19088/chuong-89/103.jpg",
    "type" : "image/jpeg",
    "bitrate" : 0,
    "duration" : 0,
    "title" : null,
    "properties" : null,
    "alternate" : [ {
      "href" : "https://i2.wp.com/img.abctruyen.xyz/uploads/19088/chuong-89/103.jpg",
      "type" : "image/jpeg",
      "bitrate" : 0,
      "duration" : 0,
      "title" : null,
      "properties" : null,
      "alternate" : null
    } ]
  }, {
    "href" : "https://img.abctruyen.xyz/uploads/19088/chuong-89/104.jpg",
    "type" : "image/jpeg",
    "bitrate" : 0,
    "duration" : 0,
    "title" : null,
    "properties" : null,
    "alternate" : [ {
      "href" : "https://i2.wp.com/img.abctruyen.xyz/uploads/19088/chuong-89/104.jpg",
      "type" : "image/jpeg",
      "bitrate" : 0,
      "duration" : 0,
      "title" : null,
      "properties" : null,
      "alternate" : null
    } ]
  }, {
    "href" : "https://img.abctruyen.xyz/uploads/19088/chuong-89/105.jpg",
    "type" : "image/jpeg",
    "bitrate" : 0,
    "duration" : 0,
    "title" : null,
    "properties" : null,
    "alternate" : [ {
      "href" : "https://i2.wp.com/img.abctruyen.xyz/uploads/19088/chuong-89/105.jpg",
      "type" : "image/jpeg",
      "bitrate" : 0,
      "duration" : 0,
      "title" : null,
      "properties" : null,
      "alternate" : null
    } ]
  }, {
    "href" : "https://img.abctruyen.xyz/uploads/19088/chuong-89/106.jpg",
    "type" : "image/jpeg",
    "bitrate" : 0,
    "duration" : 0,
    "title" : null,
    "properties" : null,
    "alternate" : [ {
      "href" : "https://i2.wp.com/img.abctruyen.xyz/uploads/19088/chuong-89/106.jpg",
      "type" : "image/jpeg",
      "bitrate" : 0,
      "duration" : 0,
      "title" : null,
      "properties" : null,
      "alternate" : null
    } ]
  }, {
    "href" : "https://img.abctruyen.xyz/uploads/19088/chuong-89/107.jpg",
    "type" : "image/jpeg",
    "bitrate" : 0,
    "duration" : 0,
    "title" : null,
    "properties" : null,
    "alternate" : [ {
      "href" : "https://i2.wp.com/img.abctruyen.xyz/uploads/19088/chuong-89/107.jpg",
      "type" : "image/jpeg",
      "bitrate" : 0,
      "duration" : 0,
      "title" : null,
      "properties" : null,
      "alternate" : null
    } ]
  }, {
    "href" : "https://img.abctruyen.xyz/uploads/19088/chuong-89/108.jpg",
    "type" : "image/jpeg",
    "bitrate" : 0,
    "duration" : 0,
    "title" : null,
    "properties" : null,
    "alternate" : [ {
      "href" : "https://i2.wp.com/img.abctruyen.xyz/uploads/19088/chuong-89/108.jpg",
      "type" : "image/jpeg",
      "bitrate" : 0,
      "duration" : 0,
      "title" : null,
      "properties" : null,
      "alternate" : null
    } ]
  }, {
    "href" : "https://img.abctruyen.xyz/uploads/19088/chuong-89/109.jpg",
    "type" : "image/jpeg",
    "bitrate" : 0,
    "duration" : 0,
    "title" : null,
    "properties" : null,
    "alternate" : [ {
      "href" : "https://i2.wp.com/img.abctruyen.xyz/uploads/19088/chuong-89/109.jpg",
      "type" : "image/jpeg",
      "bitrate" : 0,
      "duration" : 0,
      "title" : null,
      "properties" : null,
      "alternate" : null
    } ]
  }, {
    "href" : "https://img.abctruyen.xyz/uploads/19088/chuong-89/110.jpg",
    "type" : "image/jpeg",
    "bitrate" : 0,
    "duration" : 0,
    "title" : null,
    "properties" : null,
    "alternate" : [ {
      "href" : "https://i2.wp.com/img.abctruyen.xyz/uploads/19088/chuong-89/110.jpg",
      "type" : "image/jpeg",
      "bitrate" : 0,
      "duration" : 0,
      "title" : null,
      "properties" : null,
      "alternate" : null
    } ]
  }, {
    "href" : "https://img.abctruyen.xyz/uploads/19088/chuong-89/111.jpg",
    "type" : "image/jpeg",
    "bitrate" : 0,
    "duration" : 0,
    "title" : null,
    "properties" : null,
    "alternate" : [ {
      "href" : "https://i2.wp.com/img.abctruyen.xyz/uploads/19088/chuong-89/111.jpg",
      "type" : "image/jpeg",
      "bitrate" : 0,
      "duration" : 0,
      "title" : null,
      "properties" : null,
      "alternate" : null
    } ]
  }, {
    "href" : "https://img.abctruyen.xyz/uploads/19088/chuong-89/112.jpg",
    "type" : "image/jpeg",
    "bitrate" : 0,
    "duration" : 0,
    "title" : null,
    "properties" : null,
    "alternate" : [ {
      "href" : "https://i2.wp.com/img.abctruyen.xyz/uploads/19088/chuong-89/112.jpg",
      "type" : "image/jpeg",
      "bitrate" : 0,
      "duration" : 0,
      "title" : null,
      "properties" : null,
      "alternate" : null
    } ]
  }, {
    "href" : "https://img.abctruyen.xyz/uploads/19088/chuong-89/113.jpg",
    "type" : "image/jpeg",
    "bitrate" : 0,
    "duration" : 0,
    "title" : null,
    "properties" : null,
    "alternate" : [ {
      "href" : "https://i2.wp.com/img.abctruyen.xyz/uploads/19088/chuong-89/113.jpg",
      "type" : "image/jpeg",
      "bitrate" : 0,
      "duration" : 0,
      "title" : null,
      "properties" : null,
      "alternate" : null
    } ]
  }, {
    "href" : "https://img.abctruyen.xyz/uploads/19088/chuong-89/114.jpg",
    "type" : "image/jpeg",
    "bitrate" : 0,
    "duration" : 0,
    "title" : null,
    "properties" : null,
    "alternate" : [ {
      "href" : "https://i2.wp.com/img.abctruyen.xyz/uploads/19088/chuong-89/114.jpg",
      "type" : "image/jpeg",
      "bitrate" : 0,
      "duration" : 0,
      "title" : null,
      "properties" : null,
      "alternate" : null
    } ]
  }, {
    "href" : "https://img.abctruyen.xyz/uploads/19088/chuong-89/115.jpg",
    "type" : "image/jpeg",
    "bitrate" : 0,
    "duration" : 0,
    "title" : null,
    "properties" : null,
    "alternate" : [ {
      "href" : "https://i2.wp.com/img.abctruyen.xyz/uploads/19088/chuong-89/115.jpg",
      "type" : "image/jpeg",
      "bitrate" : 0,
      "duration" : 0,
      "title" : null,
      "properties" : null,
      "alternate" : null
    } ]
  }, {
    "href" : "https://img.abctruyen.xyz/uploads/19088/chuong-89/116.jpg",
    "type" : "image/jpeg",
    "bitrate" : 0,
    "duration" : 0,
    "title" : null,
    "properties" : null,
    "alternate" : [ {
      "href" : "https://i2.wp.com/img.abctruyen.xyz/uploads/19088/chuong-89/116.jpg",
      "type" : "image/jpeg",
      "bitrate" : 0,
      "duration" : 0,
      "title" : null,
      "properties" : null,
      "alternate" : null
    } ]
  }, {
    "href" : "https://img.abctruyen.xyz/uploads/19088/chuong-89/117.jpg",
    "type" : "image/jpeg",
    "bitrate" : 0,
    "duration" : 0,
    "title" : null,
    "properties" : null,
    "alternate" : [ {
      "href" : "https://i2.wp.com/img.abctruyen.xyz/uploads/19088/chuong-89/117.jpg",
      "type" : "image/jpeg",
      "bitrate" : 0,
      "duration" : 0,
      "title" : null,
      "properties" : null,
      "alternate" : null
    } ]
  }, {
    "href" : "https://img.abctruyen.xyz/uploads/19088/chuong-89/118.jpg",
    "type" : "image/jpeg",
    "bitrate" : 0,
    "duration" : 0,
    "title" : null,
    "properties" : null,
    "alternate" : [ {
      "href" : "https://i2.wp.com/img.abctruyen.xyz/uploads/19088/chuong-89/118.jpg",
      "type" : "image/jpeg",
      "bitrate" : 0,
      "duration" : 0,
      "title" : null,
      "properties" : null,
      "alternate" : null
    } ]
  }, {
    "href" : "https://img.abctruyen.xyz/uploads/19088/chuong-89/119.jpg",
    "type" : "image/jpeg",
    "bitrate" : 0,
    "duration" : 0,
    "title" : null,
    "properties" : null,
    "alternate" : [ {
      "href" : "https://i2.wp.com/img.abctruyen.xyz/uploads/19088/chuong-89/119.jpg",
      "type" : "image/jpeg",
      "bitrate" : 0,
      "duration" : 0,
      "title" : null,
      "properties" : null,
      "alternate" : null
    } ]
  }, {
    "href" : "https://img.abctruyen.xyz/uploads/19088/chuong-89/120.jpg",
    "type" : "image/jpeg",
    "bitrate" : 0,
    "duration" : 0,
    "title" : null,
    "properties" : null,
    "alternate" : [ {
      "href" : "https://i2.wp.com/img.abctruyen.xyz/uploads/19088/chuong-89/120.jpg",
      "type" : "image/jpeg",
      "bitrate" : 0,
      "duration" : 0,
      "title" : null,
      "properties" : null,
      "alternate" : null
    } ]
  }, {
    "href" : "https://img.abctruyen.xyz/uploads/19088/chuong-89/121.jpg",
    "type" : "image/jpeg",
    "bitrate" : 0,
    "duration" : 0,
    "title" : null,
    "properties" : null,
    "alternate" : [ {
      "href" : "https://i2.wp.com/img.abctruyen.xyz/uploads/19088/chuong-89/121.jpg",
      "type" : "image/jpeg",
      "bitrate" : 0,
      "duration" : 0,
      "title" : null,
      "properties" : null,
      "alternate" : null
    } ]
  }, {
    "href" : "https://img.abctruyen.xyz/uploads/19088/chuong-89/122.jpg",
    "type" : "image/jpeg",
    "bitrate" : 0,
    "duration" : 0,
    "title" : null,
    "properties" : null,
    "alternate" : [ {
      "href" : "https://i2.wp.com/img.abctruyen.xyz/uploads/19088/chuong-89/122.jpg",
      "type" : "image/jpeg",
      "bitrate" : 0,
      "duration" : 0,
      "title" : null,
      "properties" : null,
      "alternate" : null
    } ]
  }, {
    "href" : "https://img.abctruyen.xyz/uploads/19088/chuong-89/123.jpg",
    "type" : "image/jpeg",
    "bitrate" : 0,
    "duration" : 0,
    "title" : null,
    "properties" : null,
    "alternate" : [ {
      "href" : "https://i2.wp.com/img.abctruyen.xyz/uploads/19088/chuong-89/123.jpg",
      "type" : "image/jpeg",
      "bitrate" : 0,
      "duration" : 0,
      "title" : null,
      "properties" : null,
      "alternate" : null
    } ]
  }, {
    "href" : "https://img.abctruyen.xyz/uploads/19088/chuong-89/124.jpg",
    "type" : "image/jpeg",
    "bitrate" : 0,
    "duration" : 0,
    "title" : null,
    "properties" : null,
    "alternate" : [ {
      "href" : "https://i2.wp.com/img.abctruyen.xyz/uploads/19088/chuong-89/124.jpg",
      "type" : "image/jpeg",
      "bitrate" : 0,
      "duration" : 0,
      "title" : null,
      "properties" : null,
      "alternate" : null
    } ]
  }, {
    "href" : "https://img.abctruyen.xyz/uploads/19088/chuong-89/125.jpg",
    "type" : "image/jpeg",
    "bitrate" : 0,
    "duration" : 0,
    "title" : null,
    "properties" : null,
    "alternate" : [ {
      "href" : "https://i2.wp.com/img.abctruyen.xyz/uploads/19088/chuong-89/125.jpg",
      "type" : "image/jpeg",
      "bitrate" : 0,
      "duration" : 0,
      "title" : null,
      "properties" : null,
      "alternate" : null
    } ]
  }, {
    "href" : "https://img.abctruyen.xyz/uploads/19088/chuong-89/126.jpg",
    "type" : "image/jpeg",
    "bitrate" : 0,
    "duration" : 0,
    "title" : null,
    "properties" : null,
    "alternate" : [ {
      "href" : "https://i2.wp.com/img.abctruyen.xyz/uploads/19088/chuong-89/126.jpg",
      "type" : "image/jpeg",
      "bitrate" : 0,
      "duration" : 0,
      "title" : null,
      "properties" : null,
      "alternate" : null
    } ]
  }, {
    "href" : "https://img.abctruyen.xyz/uploads/19088/chuong-89/127.jpg",
    "type" : "image/jpeg",
    "bitrate" : 0,
    "duration" : 0,
    "title" : null,
    "properties" : null,
    "alternate" : [ {
      "href" : "https://i2.wp.com/img.abctruyen.xyz/uploads/19088/chuong-89/127.jpg",
      "type" : "image/jpeg",
      "bitrate" : 0,
      "duration" : 0,
      "title" : null,
      "properties" : null,
      "alternate" : null
    } ]
  }, {
    "href" : "https://img.abctruyen.xyz/uploads/19088/chuong-89/128.jpg",
    "type" : "image/jpeg",
    "bitrate" : 0,
    "duration" : 0,
    "title" : null,
    "properties" : null,
    "alternate" : [ {
      "href" : "https://i2.wp.com/img.abctruyen.xyz/uploads/19088/chuong-89/128.jpg",
      "type" : "image/jpeg",
      "bitrate" : 0,
      "duration" : 0,
      "title" : null,
      "properties" : null,
      "alternate" : null
    } ]
  }, {
    "href" : "https://img.abctruyen.xyz/uploads/19088/chuong-89/129.jpg",
    "type" : "image/jpeg",
    "bitrate" : 0,
    "duration" : 0,
    "title" : null,
    "properties" : null,
    "alternate" : [ {
      "href" : "https://i2.wp.com/img.abctruyen.xyz/uploads/19088/chuong-89/129.jpg",
      "type" : "image/jpeg",
      "bitrate" : 0,
      "duration" : 0,
      "title" : null,
      "properties" : null,
      "alternate" : null
    } ]
  }, {
    "href" : "https://img.abctruyen.xyz/uploads/19088/chuong-89/130.jpg",
    "type" : "image/jpeg",
    "bitrate" : 0,
    "duration" : 0,
    "title" : null,
    "properties" : null,
    "alternate" : [ {
      "href" : "https://i2.wp.com/img.abctruyen.xyz/uploads/19088/chuong-89/130.jpg",
      "type" : "image/jpeg",
      "bitrate" : 0,
      "duration" : 0,
      "title" : null,
      "properties" : null,
      "alternate" : null
    } ]
  }, {
    "href" : "https://img.abctruyen.xyz/uploads/19088/chuong-89/131.jpg",
    "type" : "image/jpeg",
    "bitrate" : 0,
    "duration" : 0,
    "title" : null,
    "properties" : null,
    "alternate" : [ {
      "href" : "https://i2.wp.com/img.abctruyen.xyz/uploads/19088/chuong-89/131.jpg",
      "type" : "image/jpeg",
      "bitrate" : 0,
      "duration" : 0,
      "title" : null,
      "properties" : null,
      "alternate" : null
    } ]
  }, {
    "href" : "https://img.abctruyen.xyz/uploads/19088/chuong-89/132.jpg",
    "type" : "image/jpeg",
    "bitrate" : 0,
    "duration" : 0,
    "title" : null,
    "properties" : null,
    "alternate" : [ {
      "href" : "https://i2.wp.com/img.abctruyen.xyz/uploads/19088/chuong-89/132.jpg",
      "type" : "image/jpeg",
      "bitrate" : 0,
      "duration" : 0,
      "title" : null,
      "properties" : null,
      "alternate" : null
    } ]
  }, {
    "href" : "https://img.abctruyen.xyz/uploads/19088/chuong-89/133.jpg",
    "type" : "image/jpeg",
    "bitrate" : 0,
    "duration" : 0,
    "title" : null,
    "properties" : null,
    "alternate" : [ {
      "href" : "https://i2.wp.com/img.abctruyen.xyz/uploads/19088/chuong-89/133.jpg",
      "type" : "image/jpeg",
      "bitrate" : 0,
      "duration" : 0,
      "title" : null,
      "properties" : null,
      "alternate" : null
    } ]
  }, {
    "href" : "https://img.abctruyen.xyz/uploads/19088/chuong-89/134.jpg",
    "type" : "image/jpeg",
    "bitrate" : 0,
    "duration" : 0,
    "title" : null,
    "properties" : null,
    "alternate" : [ {
      "href" : "https://i2.wp.com/img.abctruyen.xyz/uploads/19088/chuong-89/134.jpg",
      "type" : "image/jpeg",
      "bitrate" : 0,
      "duration" : 0,
      "title" : null,
      "properties" : null,
      "alternate" : null
    } ]
  }, {
    "href" : "https://img.abctruyen.xyz/uploads/19088/chuong-89/135.jpg",
    "type" : "image/jpeg",
    "bitrate" : 0,
    "duration" : 0,
    "title" : null,
    "properties" : null,
    "alternate" : [ {
      "href" : "https://i2.wp.com/img.abctruyen.xyz/uploads/19088/chuong-89/135.jpg",
      "type" : "image/jpeg",
      "bitrate" : 0,
      "duration" : 0,
      "title" : null,
      "properties" : null,
      "alternate" : null
    } ]
  }, {
    "href" : "https://img.abctruyen.xyz/uploads/19088/chuong-89/136.jpg",
    "type" : "image/jpeg",
    "bitrate" : 0,
    "duration" : 0,
    "title" : null,
    "properties" : null,
    "alternate" : [ {
      "href" : "https://i2.wp.com/img.abctruyen.xyz/uploads/19088/chuong-89/136.jpg",
      "type" : "image/jpeg",
      "bitrate" : 0,
      "duration" : 0,
      "title" : null,
      "properties" : null,
      "alternate" : null
    } ]
  }, {
    "href" : "https://img.abctruyen.xyz/uploads/19088/chuong-89/137.jpg",
    "type" : "image/jpeg",
    "bitrate" : 0,
    "duration" : 0,
    "title" : null,
    "properties" : null,
    "alternate" : [ {
      "href" : "https://i2.wp.com/img.abctruyen.xyz/uploads/19088/chuong-89/137.jpg",
      "type" : "image/jpeg",
      "bitrate" : 0,
      "duration" : 0,
      "title" : null,
      "properties" : null,
      "alternate" : null
    } ]
  }, {
    "href" : "https://img.abctruyen.xyz/uploads/19088/chuong-89/138.jpg",
    "type" : "image/jpeg",
    "bitrate" : 0,
    "duration" : 0,
    "title" : null,
    "properties" : null,
    "alternate" : [ {
      "href" : "https://i2.wp.com/img.abctruyen.xyz/uploads/19088/chuong-89/138.jpg",
      "type" : "image/jpeg",
      "bitrate" : 0,
      "duration" : 0,
      "title" : null,
      "properties" : null,
      "alternate" : null
    } ]
  }, {
    "href" : "https://img.abctruyen.xyz/uploads/19088/chuong-89/139.jpg",
    "type" : "image/jpeg",
    "bitrate" : 0,
    "duration" : 0,
    "title" : null,
    "properties" : null,
    "alternate" : [ {
      "href" : "https://i2.wp.com/img.abctruyen.xyz/uploads/19088/chuong-89/139.jpg",
      "type" : "image/jpeg",
      "bitrate" : 0,
      "duration" : 0,
      "title" : null,
      "properties" : null,
      "alternate" : null
    } ]
  }, {
    "href" : "https://img.abctruyen.xyz/uploads/19088/chuong-89/140.jpg",
    "type" : "image/jpeg",
    "bitrate" : 0,
    "duration" : 0,
    "title" : null,
    "properties" : null,
    "alternate" : [ {
      "href" : "https://i2.wp.com/img.abctruyen.xyz/uploads/19088/chuong-89/140.jpg",
      "type" : "image/jpeg",
      "bitrate" : 0,
      "duration" : 0,
      "title" : null,
      "properties" : null,
      "alternate" : null
    } ]
  }, {
    "href" : "https://img.abctruyen.xyz/uploads/19088/chuong-89/141.jpg",
    "type" : "image/jpeg",
    "bitrate" : 0,
    "duration" : 0,
    "title" : null,
    "properties" : null,
    "alternate" : [ {
      "href" : "https://i2.wp.com/img.abctruyen.xyz/uploads/19088/chuong-89/141.jpg",
      "type" : "image/jpeg",
      "bitrate" : 0,
      "duration" : 0,
      "title" : null,
      "properties" : null,
      "alternate" : null
    } ]
  }, {
    "href" : "https://img.abctruyen.xyz/uploads/19088/chuong-89/142.jpg",
    "type" : "image/jpeg",
    "bitrate" : 0,
    "duration" : 0,
    "title" : null,
    "properties" : null,
    "alternate" : [ {
      "href" : "https://i2.wp.com/img.abctruyen.xyz/uploads/19088/chuong-89/142.jpg",
      "type" : "image/jpeg",
      "bitrate" : 0,
      "duration" : 0,
      "title" : null,
      "properties" : null,
      "alternate" : null
    } ]
  }, {
    "href" : "https://img.abctruyen.xyz/uploads/19088/chuong-89/143.jpg",
    "type" : "image/jpeg",
    "bitrate" : 0,
    "duration" : 0,
    "title" : null,
    "properties" : null,
    "alternate" : [ {
      "href" : "https://i2.wp.com/img.abctruyen.xyz/uploads/19088/chuong-89/143.jpg",
      "type" : "image/jpeg",
      "bitrate" : 0,
      "duration" : 0,
      "title" : null,
      "properties" : null,
      "alternate" : null
    } ]
  }, {
    "href" : "https://img.abctruyen.xyz/uploads/19088/chuong-89/144.jpg",
    "type" : "image/jpeg",
    "bitrate" : 0,
    "duration" : 0,
    "title" : null,
    "properties" : null,
    "alternate" : [ {
      "href" : "https://i2.wp.com/img.abctruyen.xyz/uploads/19088/chuong-89/144.jpg",
      "type" : "image/jpeg",
      "bitrate" : 0,
      "duration" : 0,
      "title" : null,
      "properties" : null,
      "alternate" : null
    } ]
  } ],
  "toc" : null,
  "@context" : "https://readium.org/webpub-manifest/context.jsonld"
}